bracketdrawer/__init__.py
bracketdrawer/logic.py
BracketDrawer-0.1.3.1.dist-info/LICENSE
BracketDrawer-0.1.3.1.dist-info/METADATA
BracketDrawer-0.1.3.1.dist-info/WHEEL
BracketDrawer-0.1.3.1.dist-info/top_level.txt
BracketDrawer-0.1.3.1.dist-info/RECORD
