Metadata-Version: 2.2
Name: BracketDrawer
Version: 0.1.3.1
Summary: A Python Package to easily create tournament brackets
Home-page: https://github.com/bendemouth/BracketDrawer
Author: Ben DeMouth
Author-email: bendemouth@gmail.com
Classifier: Programming Language :: Python :: 3
Requires-Python: >=3.7
License-File: LICENSE
Requires-Dist: matplotlib
Requires-Dist: pandas
Dynamic: author
Dynamic: author-email
Dynamic: home-page
